petstoreapi/__init__.py
petstoreapi/api.py
petstoreapi/generate.py
petstoreapi-0.0.10.dist-info/METADATA
petstoreapi-0.0.10.dist-info/WHEEL
petstoreapi-0.0.10.dist-info/top_level.txt
petstoreapi-0.0.10.dist-info/RECORD
