Metadata-Version: 2.1
Name: petstoreapi
Version: 0.0.10
Summary: An async API wrapper for the petstore microservice.
Author: PandasAreBears
Keywords: wrapper,api,async,petstore,microservice
Requires-Python: >=3.5
Requires-Dist: pydantic
Requires-Dist: faker
Requires-Dist: aiohttp
Requires-Dist: gptfunction
Requires-Dist: petstoremodels
Requires-Dist: random-username
Requires-Dist: requests
